python_gql_gen/__init__.py
python_gql_gen/cli.py
python_gql_gen/python_gql_gen.py
python_gql_gen/utils.py
python_gql_gen-0.1.2.dist-info/AUTHORS.rst
python_gql_gen-0.1.2.dist-info/LICENSE
python_gql_gen-0.1.2.dist-info/METADATA
python_gql_gen-0.1.2.dist-info/WHEEL
python_gql_gen-0.1.2.dist-info/entry_points.txt
python_gql_gen-0.1.2.dist-info/top_level.txt
python_gql_gen-0.1.2.dist-info/RECORD
